xmltool/__init__.py
xmltool/cache.py
xmltool/dtd.py
xmltool/dtd_parser.py
xmltool/elements.py
xmltool/factory.py
xmltool/testbase.py
xmltool/utils.py
xmltool-1.1.0.dist-info/LICENSE.txt
xmltool-1.1.0.dist-info/METADATA
xmltool-1.1.0.dist-info/WHEEL
xmltool-1.1.0.dist-info/top_level.txt
xmltool-1.1.0.dist-info/RECORD
